{
  "generated_at": "2026-07-07T15:34:49",
  "date": "2026-07-07",
  "market_sentiment": {
    "indices": {
      "S&P 500": {
        "symbol": "^GSPC",
        "last": 7487.81,
        "pct_change": -0.66
      },
      "Nasdaq": {
        "symbol": "^IXIC",
        "last": 25761.65,
        "pct_change": -1.38
      },
      "Dow Jones": {
        "symbol": "^DJI",
        "last": 52833.48,
        "pct_change": -0.42
      },
      "Russell 2000": {
        "symbol": "^RUT",
        "last": 2986.55,
        "pct_change": -0.76
      },
      "VIX": {
        "symbol": "^VIX",
        "last": 16.43,
        "pct_change": 5.52
      },
      "10Y Treasury Yield": {
        "symbol": "^TNX",
        "last": 4.51,
        "pct_change": 0.62
      },
      "US Dollar Index": {
        "symbol": "DX-Y.NYB",
        "last": 100.96,
        "pct_change": 0.11
      },
      "Crude Oil WTI": {
        "symbol": "CL=F",
        "last": 70.41,
        "pct_change": 2.71
      },
      "Gold": {
        "symbol": "GC=F",
        "last": 4155.6,
        "pct_change": 0.01
      }
    },
    "sectors": {
      "Technology": {
        "symbol": "XLK",
        "last": 178.31,
        "pct_change": -2.87
      },
      "Financials": {
        "symbol": "XLF",
        "last": 56.28,
        "pct_change": 0.24
      },
      "Energy": {
        "symbol": "XLE",
        "last": 54.02,
        "pct_change": 1.68
      },
      "Health Care": {
        "symbol": "XLV",
        "last": 164.63,
        "pct_change": 1.65
      },
      "Consumer Discretionary": {
        "symbol": "XLY",
        "last": 117.29,
        "pct_change": -0.61
      },
      "Consumer Staples": {
        "symbol": "XLP",
        "last": 85.12,
        "pct_change": 1.22
      },
      "Industrials": {
        "symbol": "XLI",
        "last": 180.83,
        "pct_change": -2.55
      },
      "Utilities": {
        "symbol": "XLU",
        "last": 46.04,
        "pct_change": 1.63
      },
      "Materials": {
        "symbol": "XLB",
        "last": 51.42,
        "pct_change": -1.08
      },
      "Real Estate": {
        "symbol": "XLRE",
        "last": 45.06,
        "pct_change": 1.73
      },
      "Communication Services": {
        "symbol": "XLC",
        "last": 111.46,
        "pct_change": 1.13
      }
    }
  },
  "japan_market": {
    "indices": {
      "Nikkei 225": {
        "symbol": "^N225",
        "last": 69737.69,
        "pct_change": -0.01
      },
      "TOPIX (ETF代理)": {
        "symbol": "1306.T",
        "last": 431.8,
        "pct_change": -0.83
      },
      "USD/JPY": {
        "symbol": "JPY=X",
        "last": 161.9,
        "pct_change": 0.28
      }
    }
  },
  "rates": {
    "us": {
      "effr": 3.63,
      "target_low": 3.5,
      "target_high": 3.75,
      "as_of": "2026-07-06"
    },
    "japan": {
      "yield": 2.823,
      "as_of": "2026-07-06",
      "prev_yield": 2.768
    },
    "spread_10y": 1.69
  },
  "watchlist": {
    "holdings": {
      "Corning (持仓)": {
        "symbol": "GLW",
        "last": 183.4,
        "pct_change": -5.85
      }
    },
    "demand_drivers": {
      "Apple": {
        "symbol": "AAPL",
        "last": 313.93,
        "pct_change": 0.41
      },
      "Microsoft": {
        "symbol": "MSFT",
        "last": 392.58,
        "pct_change": 1.51
      },
      "Amazon": {
        "symbol": "AMZN",
        "last": 243.05,
        "pct_change": -0.45
      },
      "Alphabet": {
        "symbol": "GOOGL",
        "last": 369.0,
        "pct_change": 0.69
      },
      "Meta": {
        "symbol": "META",
        "last": 605.11,
        "pct_change": 0.8
      }
    },
    "peers": {
      "Lumentum": {
        "symbol": "LITE",
        "last": 698.17,
        "pct_change": -4.52
      },
      "Coherent": {
        "symbol": "COHR",
        "last": 314.45,
        "pct_change": -6.33
      },
      "Amphenol": {
        "symbol": "APH",
        "last": 157.79,
        "pct_change": -5.41
      },
      "AGC旭硝子(东京上市)": {
        "symbol": "5201.T",
        "last": 6737.0,
        "pct_change": -2.15
      }
    }
  },
  "economic_calendar": [
    {
      "title": "Final Services PMI",
      "country": "USD",
      "date": "2026-07-06T09:45:00-04:00",
      "impact": "Low",
      "forecast": "51.4",
      "previous": "51.3"
    },
    {
      "title": "ISM Services PMI",
      "country": "USD",
      "date": "2026-07-06T10:00:00-04:00",
      "impact": "High",
      "forecast": "54.2",
      "previous": "54.5"
    },
    {
      "title": "FOMC Member Waller Speaks",
      "country": "USD",
      "date": "2026-07-06T11:00:00-04:00",
      "impact": "Low",
      "forecast": "",
      "previous": ""
    },
    {
      "title": "Average Cash Earnings y/y",
      "country": "JPY",
      "date": "2026-07-06T19:30:00-04:00",
      "impact": "Low",
      "forecast": "3.4%",
      "previous": "3.5%"
    },
    {
      "title": "Household Spending y/y",
      "country": "JPY",
      "date": "2026-07-06T19:30:00-04:00",
      "impact": "Low",
      "forecast": "-2.3%",
      "previous": "-0.5%"
    },
    {
      "title": "30-y Bond Auction",
      "country": "JPY",
      "date": "2026-07-06T23:35:00-04:00",
      "impact": "Low",
      "forecast": "",
      "previous": "3.86|2.9"
    },
    {
      "title": "Leading Indicators",
      "country": "JPY",
      "date": "2026-07-07T01:00:00-04:00",
      "impact": "Low",
      "forecast": "116.9%",
      "previous": "115.9%"
    },
    {
      "title": "FOMC Member Bowman Speaks",
      "country": "USD",
      "date": "2026-07-07T07:00:00-04:00",
      "impact": "Low",
      "forecast": "",
      "previous": ""
    },
    {
      "title": "ADP Weekly Employment Change",
      "country": "USD",
      "date": "2026-07-07T08:14:00-04:00",
      "impact": "Low",
      "forecast": "",
      "previous": "30.8K"
    },
    {
      "title": "ADP Weekly Employment Change",
      "country": "USD",
      "date": "2026-07-07T08:15:00-04:00",
      "impact": "Low",
      "forecast": "",
      "previous": "24.3K"
    },
    {
      "title": "Trade Balance",
      "country": "USD",
      "date": "2026-07-07T08:30:00-04:00",
      "impact": "Low",
      "forecast": "-78.3B",
      "previous": "-55.9B"
    },
    {
      "title": "RCM/TIPP Economic Optimism",
      "country": "USD",
      "date": "2026-07-07T10:04:00-04:00",
      "impact": "Low",
      "forecast": "45.0",
      "previous": "42.5"
    },
    {
      "title": "API Weekly Statistical Bulletin",
      "country": "USD",
      "date": "2026-07-07T16:30:00-04:00",
      "impact": "Low",
      "forecast": "",
      "previous": ""
    },
    {
      "title": "Bank Lending y/y",
      "country": "JPY",
      "date": "2026-07-07T19:50:00-04:00",
      "impact": "Low",
      "forecast": "5.8%",
      "previous": "5.7%"
    },
    {
      "title": "Current Account",
      "country": "JPY",
      "date": "2026-07-07T19:50:00-04:00",
      "impact": "Low",
      "forecast": "3.19T",
      "previous": "4.21T"
    },
    {
      "title": "Economy Watchers Sentiment",
      "country": "JPY",
      "date": "2026-07-08T01:00:00-04:00",
      "impact": "Low",
      "forecast": "44.3",
      "previous": "43.6"
    },
    {
      "title": "Final Wholesale Inventories m/m",
      "country": "USD",
      "date": "2026-07-08T10:00:00-04:00",
      "impact": "Low",
      "forecast": "0.3%",
      "previous": "0.3%"
    },
    {
      "title": "Crude Oil Inventories",
      "country": "USD",
      "date": "2026-07-08T10:30:00-04:00",
      "impact": "Low",
      "forecast": "-1.0M",
      "previous": "-3.8M"
    },
    {
      "title": "10-y Bond Auction",
      "country": "USD",
      "date": "2026-07-08T13:01:00-04:00",
      "impact": "Low",
      "forecast": "",
      "previous": "4.54|2.6"
    },
    {
      "title": "FOMC Meeting Minutes",
      "country": "USD",
      "date": "2026-07-08T14:00:00-04:00",
      "impact": "High",
      "forecast": "",
      "previous": ""
    },
    {
      "title": "Consumer Credit m/m",
      "country": "USD",
      "date": "2026-07-08T15:00:00-04:00",
      "impact": "Low",
      "forecast": "16.9B",
      "previous": "20.7B"
    },
    {
      "title": "M2 Money Stock y/y",
      "country": "JPY",
      "date": "2026-07-08T19:50:00-04:00",
      "impact": "Low",
      "forecast": "2.4%",
      "previous": "2.5%"
    },
    {
      "title": "Prelim Machine Tool Orders y/y",
      "country": "JPY",
      "date": "2026-07-09T02:00:00-04:00",
      "impact": "Low",
      "forecast": "",
      "previous": "37.4%"
    },
    {
      "title": "Unemployment Claims",
      "country": "USD",
      "date": "2026-07-09T08:30:00-04:00",
      "impact": "Medium",
      "forecast": "218K",
      "previous": "215K"
    },
    {
      "title": "FOMC Member Williams Speaks",
      "country": "USD",
      "date": "2026-07-09T09:00:00-04:00",
      "impact": "Low",
      "forecast": "",
      "previous": ""
    },
    {
      "title": "Existing Home Sales",
      "country": "USD",
      "date": "2026-07-09T10:00:00-04:00",
      "impact": "Low",
      "forecast": "4.19M",
      "previous": "4.17M"
    },
    {
      "title": "Natural Gas Storage",
      "country": "USD",
      "date": "2026-07-09T10:30:00-04:00",
      "impact": "Low",
      "forecast": "",
      "previous": "87B"
    },
    {
      "title": "30-y Bond Auction",
      "country": "USD",
      "date": "2026-07-09T13:01:00-04:00",
      "impact": "Low",
      "forecast": "",
      "previous": "5.02|2.3"
    },
    {
      "title": "PPI y/y",
      "country": "JPY",
      "date": "2026-07-09T19:50:00-04:00",
      "impact": "Low",
      "forecast": "6.8%",
      "previous": "6.3%"
    },
    {
      "title": "Fed Monetary Policy Report",
      "country": "USD",
      "date": "2026-07-10T11:00:00-04:00",
      "impact": "Low",
      "forecast": "",
      "previous": ""
    }
  ],
  "fed_policy": {
    "Press Releases": [
      {
        "title": "Federal Reserve Board issues enforcement action with Small Business Bank and announces termination enforcement actions with BNP Paribas S.A., BNP Paribas USA, Inc., BNP Paribas Securities Corp., and Community Bankshares, Inc.",
        "link": "https://www.federalreserve.gov/newsevents/pressreleases/enforcement20260702a.htm",
        "published": "Thu, 2 Jul 2026 15:00:00 GMT",
        "summary": "Federal Reserve Board issues enforcement action with Small Business Bank and announces termination enforcement actions with BNP Paribas S.A., BNP Paribas USA, Inc., BNP Paribas Securities Corp., and Community Bankshares, Inc."
      },
      {
        "title": "Federal Reserve issues initial findings from its 2025 triennial payments study",
        "link": "https://www.federalreserve.gov/newsevents/pressreleases/other20260701a.htm",
        "published": "Wed, 1 Jul 2026 18:30:00 GMT",
        "summary": "Federal Reserve issues initial findings from its 2025 triennial payments study"
      },
      {
        "title": "Agencies release list of distressed or underserved nonmetropolitan middle-income geographies",
        "link": "https://www.federalreserve.gov/newsevents/pressreleases/bcreg20260630a.htm",
        "published": "Tue, 30 Jun 2026 14:00:00 GMT",
        "summary": "Agencies release list of distressed or underserved nonmetropolitan middle-income geographies"
      },
      {
        "title": "Federal Reserve Board issues enforcement action with employee of Bank of Eufaula and S N B Bancshares, Inc.",
        "link": "https://www.federalreserve.gov/newsevents/pressreleases/enforcement20260625b.htm",
        "published": "Thu, 25 Jun 2026 15:00:00 GMT",
        "summary": "Federal Reserve Board issues enforcement action with employee of Bank of Eufaula and S N B Bancshares, Inc."
      },
      {
        "title": "Federal Reserve Board announces termination of enforcement action with Jiko Group, Inc.",
        "link": "https://www.federalreserve.gov/newsevents/pressreleases/enforcement20260625a.htm",
        "published": "Thu, 25 Jun 2026 15:00:00 GMT",
        "summary": "Federal Reserve Board announces termination of enforcement action with Jiko Group, Inc."
      },
      {
        "title": "Federal Reserve Board's annual bank stress test confirms that large banks are well positioned to weather a severe recession and able to continue to lend to households and businesses",
        "link": "https://www.federalreserve.gov/newsevents/pressreleases/bcreg20260624a.htm",
        "published": "Wed, 24 Jun 2026 20:00:00 GMT",
        "summary": "Federal Reserve Board's annual bank stress test confirms that large banks are well positioned to weather a severe recession and able to continue to lend to households and businesses"
      },
      {
        "title": "Federal Reserve notes with deep sadness the passing of Alan Greenspan",
        "link": "https://www.federalreserve.gov/newsevents/pressreleases/other20260622a.htm",
        "published": "Mon, 22 Jun 2026 12:45:00 GMT",
        "summary": "Federal Reserve notes with deep sadness the passing of Alan Greenspan"
      },
      {
        "title": "Federal Reserve Board issues enforcement action with former employee of Bank of Eufaula and S N B Bancshares, Inc.",
        "link": "https://www.federalreserve.gov/newsevents/pressreleases/enforcement20260618b.htm",
        "published": "Thu, 18 Jun 2026 19:00:00 GMT",
        "summary": "Federal Reserve Board issues enforcement action with former employee of Bank of Eufaula and S N B Bancshares, Inc."
      }
    ],
    "Speeches": [
      {
        "title": "Bowman, Opening Remarks on Sound Practices for Artificial Intelligence",
        "link": "https://www.federalreserve.gov/newsevents/speech/bowman20260707a.htm",
        "published": "Tue, 7 Jul 2026 11:00:00 GMT",
        "summary": "Speech At the Financial Stability Board Virtual Outreach Event"
      },
      {
        "title": "Waller, Two Thoughts on the Transmission of Monetary Policy",
        "link": "https://www.federalreserve.gov/newsevents/speech/waller20260706a.htm",
        "published": "Mon, 6 Jul 2026 15:00:00 GMT",
        "summary": "Speech At &quot;Challenges for Monetary Policy Transmission in a Changing World,&quot; a conference sponsored by the Bank of Italy for the research network initiated by the European System of Central Banks, Rome, Italy"
      },
      {
        "title": "Cook, Welcome Remarks",
        "link": "https://www.federalreserve.gov/newsevents/speech/cook20260624a.htm",
        "published": "Wed, 24 Jun 2026 18:00:00 GMT",
        "summary": "Speech At the State of Small Business Symposium hosted by the Federal Reserve Bank of Cleveland (via pre-recorded video)"
      },
      {
        "title": "Waller, Welcoming Remarks on the International Role of the U.S. Dollar",
        "link": "https://www.federalreserve.gov/newsevents/speech/waller20260622a.htm",
        "published": "Mon, 22 Jun 2026 13:00:00 GMT",
        "summary": "Speech At the Fifth Conference on the International Roles of the Dollar, Board of Governors of the Federal Reserve System, Washington, D.C."
      },
      {
        "title": "Barr, Deregulating in a Financial Boom: What Could Go Wrong?",
        "link": "https://www.federalreserve.gov/newsevents/speech/barr20260606a.htm",
        "published": "Sat, 6 Jun 2026 16:00:00 GMT",
        "summary": "Speech At American University, Washington, D.C."
      },
      {
        "title": "Powell, Acceptance Remarks",
        "link": "https://www.federalreserve.gov/newsevents/speech/powell20260531a.htm",
        "published": "Mon, 1 Jun 2026 00:30:00 GMT",
        "summary": "Speech For the 2026 John F. Kennedy Profile in Courage Award, John F. Kennedy Library Foundation, Boston, Massachusetts"
      },
      {
        "title": "Bowman, A Framework for Practical Monetary Policy Decision Making",
        "link": "https://www.federalreserve.gov/newsevents/speech/bowman20260529a.htm",
        "published": "Fri, 29 May 2026 13:10:00 GMT",
        "summary": "Speech At the Reykjav&iacute;k Economic Conference 2026, Central Bank of Iceland, Reykjav&iacute;k, Iceland"
      },
      {
        "title": "Jefferson, Global Economic Developments and the U.S. Economy",
        "link": "https://www.federalreserve.gov/newsevents/speech/jefferson20260527a.htm",
        "published": "Thu, 28 May 2026 00:00:00 GMT",
        "summary": "Speech At the 2026 Bank of Japan-Institute for Monetary and Economic Studies Conference, Tokyo, Japan"
      }
    ],
    "FOMC Press Releases": [
      {
        "title": "Federal Reserve issues FOMC statement",
        "link": "https://www.federalreserve.gov/newsevents/pressreleases/monetary20260617a.htm",
        "published": "Wed, 17 Jun 2026 18:00:00 GMT",
        "summary": "Federal Reserve issues FOMC statement"
      },
      {
        "title": "Federal Reserve Board and Federal Open Market Committee release economic projections from the June 16-17 FOMC meeting",
        "link": "https://www.federalreserve.gov/newsevents/pressreleases/monetary20260617b.htm",
        "published": "Wed, 17 Jun 2026 18:00:00 GMT",
        "summary": "Federal Reserve Board and Federal Open Market Committee release economic projections from the June 16-17 FOMC meeting"
      },
      {
        "title": "Minutes of the Board's discount rate meeting on April 20 and 29, 2026",
        "link": "https://www.federalreserve.gov/newsevents/pressreleases/monetary20260526a.htm",
        "published": "Tue, 26 May 2026 18:00:00 GMT",
        "summary": "Minutes of the Board's discount rate meeting on April 20 and 29, 2026"
      },
      {
        "title": "Minutes of the Federal Open Market Committee, April 28-29, 2026",
        "link": "https://www.federalreserve.gov/newsevents/pressreleases/monetary20260520a.htm",
        "published": "Wed, 20 May 2026 18:00:00 GMT",
        "summary": "Minutes of the Federal Open Market Committee, April 28-29, 2026"
      },
      {
        "title": "Federal Reserve issues FOMC statement",
        "link": "https://www.federalreserve.gov/newsevents/pressreleases/monetary20260429a.htm",
        "published": "Wed, 29 Apr 2026 18:00:00 GMT",
        "summary": "Federal Reserve issues FOMC statement"
      },
      {
        "title": "Minutes of the Board’s discount rate meetings on February 9 and March 18, 2026",
        "link": "https://www.federalreserve.gov/newsevents/pressreleases/monetary20260414a.htm",
        "published": "Tue, 14 Apr 2026 18:00:00 GMT",
        "summary": "Minutes of the Board’s discount rate meetings on February 9 and March 18, 2026"
      },
      {
        "title": "Minutes of the Federal Open Market Committee, March 17–18, 2026",
        "link": "https://www.federalreserve.gov/newsevents/pressreleases/monetary20260408a.htm",
        "published": "Wed, 8 Apr 2026 18:00:00 GMT",
        "summary": "Minutes of the Federal Open Market Committee, March 17–18, 2026"
      },
      {
        "title": "Federal Reserve issues FOMC statement",
        "link": "https://www.federalreserve.gov/newsevents/pressreleases/monetary20260318a.htm",
        "published": "Wed, 18 Mar 2026 18:00:00 GMT",
        "summary": "Federal Reserve issues FOMC statement"
      }
    ]
  },
  "news": {
    "Yahoo Finance": [
      {
        "title": "Best Buy and Apple flag a price shock for shoppers",
        "link": "https://finance.yahoo.com/economy/articles/best-buy-apple-flag-price-203300039.html",
        "published": "2026-07-06T20:33:00Z"
      },
      {
        "title": "Texas hits Walmart with $13M settlement over delivery driver pay",
        "link": "https://finance.yahoo.com/small-business/articles/texas-hits-walmart-13m-settlement-151047806.html",
        "published": "2026-07-07T15:10:47Z"
      },
      {
        "title": "NY Fed survey reports rising near-term inflation expectations in June",
        "link": "https://finance.yahoo.com/economy/policy/articles/ny-fed-survey-reports-rising-150354569.html",
        "published": "2026-07-07T15:03:54Z"
      },
      {
        "title": "Consumers dread rising healthcare, rent costs: New York Fed",
        "link": "https://finance.yahoo.com/economy/article/consumers-dread-rising-healthcare-rent-costs-new-york-fed-150000217.html",
        "published": "2026-07-07T15:00:00Z"
      },
      {
        "title": "Stock market today: Nasdaq leads Dow, S&P 500 lower after Samsung results spark chip sell-off",
        "link": "https://finance.yahoo.com/markets/live/stock-market-today-sp-500-nasdaq-futures-slip-after-samsung-results-spark-chip-sell-off-223015294.html",
        "published": "2026-07-06T22:30:15Z"
      },
      {
        "title": "Chipotle vs. McDonald’s: Why the Stock with Negative Comps Is the Better Buy",
        "link": "https://finance.yahoo.com/markets/stocks/articles/chipotle-vs-mcdonald-why-stock-152817158.html",
        "published": "2026-07-07T15:28:17Z"
      },
      {
        "title": "Mercado Bitcoin Lands $20M From Tether for Tokenization and Payments Expansion",
        "link": "https://finance.yahoo.com/markets/crypto/articles/mercado-bitcoin-lands-20m-tether-145200217.html",
        "published": "2026-07-07T14:52:00Z"
      },
      {
        "title": "Abacus Tokenizes Life Insurance Assets as $224B Market Moves Onchain",
        "link": "https://finance.yahoo.com/markets/crypto/articles/abacus-tokenizes-life-insurance-assets-144900743.html",
        "published": "2026-07-07T14:49:00Z"
      }
    ],
    "MarketWatch Top Stories": [
      {
        "title": "NATO announces billions in defense deals. What investors should watch for now.",
        "link": "https://www.marketwatch.com/story/nato-announces-billions-in-defense-deals-what-investors-should-watch-for-now-d7f3c4be?mod=mw_rss_topstories",
        "published": "Tue, 07 Jul 2026 15:06:00 GMT"
      },
      {
        "title": "‘Our family is broken beyond repair’: My brother took over my parents’ finances. What can I do?",
        "link": "https://www.marketwatch.com/story/our-family-is-broken-beyond-repair-my-brother-took-over-my-parents-finances-what-can-i-do-95239fb9?mod=mw_rss_topstories",
        "published": "Tue, 07 Jul 2026 15:00:00 GMT"
      },
      {
        "title": "I found a simple way to save money on frozen pizza. What’s your best money-saving trick?",
        "link": "https://www.marketwatch.com/story/i-make-my-own-pizza-whats-the-best-way-youve-found-to-save-money-25412399?mod=mw_rss_topstories",
        "published": "Tue, 07 Jul 2026 14:30:00 GMT"
      },
      {
        "title": "Micron’s stock falls as investors wonder if the memory market is near the top",
        "link": "https://www.marketwatch.com/story/microns-stock-falls-as-investors-wonder-if-the-memory-market-is-near-the-top-ab2d2feb?mod=mw_rss_topstories",
        "published": "Tue, 07 Jul 2026 14:29:00 GMT"
      },
      {
        "title": "How parents can take advantage of the ‘best summer-camp tax break in years’",
        "link": "https://www.marketwatch.com/story/how-parents-can-take-advantage-of-the-best-summer-camp-tax-break-in-years-cb7c2a1a?mod=mw_rss_topstories",
        "published": "Tue, 07 Jul 2026 14:27:00 GMT"
      },
      {
        "title": "Who should handle your estate plan: Your lawyer or your financial adviser?",
        "link": "https://www.marketwatch.com/story/who-should-handle-your-estate-plan-your-lawyer-or-your-financial-adviser-134189d7?mod=mw_rss_topstories",
        "published": "Tue, 07 Jul 2026 14:22:00 GMT"
      },
      {
        "title": "We’re spending $7,000 to attend 7 weddings this year — and that’s after cutting corners",
        "link": "https://www.marketwatch.com/story/were-spending-7-000-to-attend-7-weddings-this-year-and-thats-after-cutting-corners-8e467037?mod=mw_rss_topstories",
        "published": "Tue, 07 Jul 2026 14:20:00 GMT"
      },
      {
        "title": "Your 5 biggest ‘Trump account’ questions, answered",
        "link": "https://www.marketwatch.com/story/your-5-biggest-questions-about-trump-accounts-answered-421d9f6f?mod=mw_rss_topstories",
        "published": "Tue, 07 Jul 2026 14:17:00 GMT"
      }
    ],
    "CNBC Top News": [
      {
        "title": "Trump renews Greenland threats at NATO summit, says U.S. could remove troops from Europe",
        "link": "https://www.cnbc.com/2026/07/07/trump-nato-summit-greenland-us-troops-europe.html",
        "published": "Tue, 07 Jul 2026 14:56:47 GMT"
      },
      {
        "title": "Chinese lidar maker with Nvidia ties accused of being cyber risk for U.S.",
        "link": "https://www.cnbc.com/2026/07/07/hesai-technology-nvidia-cyber-risk.html",
        "published": "Tue, 07 Jul 2026 12:00:01 GMT"
      },
      {
        "title": "Stellantis to sell small Fiat Topolino EV for $13,995 in U.S.",
        "link": "https://www.cnbc.com/2026/07/07/stellantis-fiat-topolino-ev.html",
        "published": "Tue, 07 Jul 2026 15:33:41 GMT"
      },
      {
        "title": "Dow turns red as chip stocks tumble, oil prices gain: Live updates",
        "link": "https://www.cnbc.com/2026/07/06/stock-market-today-live-updates.html",
        "published": "Tue, 07 Jul 2026 15:17:42 GMT"
      },
      {
        "title": "Only one SpaceX analyst out of all the bulls Tuesday is calling for the stock to drop. Here's why",
        "link": "https://www.cnbc.com/2026/07/07/only-one-spacex-analyst-is-calling-for-the-stock-to-drop-heres-why.html",
        "published": "Tue, 07 Jul 2026 14:06:20 GMT"
      },
      {
        "title": "Rivian stock falls more than 10% as company sells 75 million shares to raise capital",
        "link": "https://www.cnbc.com/2026/07/07/rivian-stock-rivn-capital-raise.html",
        "published": "Tue, 07 Jul 2026 13:54:34 GMT"
      },
      {
        "title": "Trump ally Nigel Farage quits UK parliament amid finance scandal to fight special election",
        "link": "https://www.cnbc.com/2026/07/07/nigel-farage-parliament-election.html",
        "published": "Tue, 07 Jul 2026 14:00:15 GMT"
      },
      {
        "title": "Amazon raising at least $25 billion in bond sale, won't issue more debt in 2026",
        "link": "https://www.cnbc.com/2026/07/07/amazon-bond-sale-ai-debt.html",
        "published": "Tue, 07 Jul 2026 14:43:19 GMT"
      }
    ]
  }
}